androide/__init__.py
androide/android_enhanced.py
androide/android_sdk_helper.py
androide/main.py
androide/output_helper.py
androide/platform_helper.py
androide/version.txt
androidtool-1.3.7.dist-info/METADATA
androidtool-1.3.7.dist-info/WHEEL
androidtool-1.3.7.dist-info/entry_points.txt
androidtool-1.3.7.dist-info/top_level.txt
androidtool-1.3.7.dist-info/zip-safe
androidtool-1.3.7.dist-info/RECORD
