Metadata-Version: 2.1
Name: androidtool
Version: 1.3.7
Summary: UNKNOWN
Home-page: https://github.com/ashishb/androidtool
Author: Ashish Bhatia
Author-email: ashishb@ashishb.net
License: Apache
Keywords: Android ADB developer
Platform: UNKNOWN
Classifier: Intended Audience :: Developers
Requires-Dist: docopt
Requires-Dist: psutil
Requires-Dist: typing
